LICENSE
MANIFEST.in
NEWS
README.rst
setup.cfg
setup.py
sphinxcontrib/__init__.py
sphinxcontrib/openstreetmap.py
sphinxcontrib_openstreetmap.egg-info/PKG-INFO
sphinxcontrib_openstreetmap.egg-info/SOURCES.txt
sphinxcontrib_openstreetmap.egg-info/dependency_links.txt
sphinxcontrib_openstreetmap.egg-info/namespace_packages.txt
sphinxcontrib_openstreetmap.egg-info/not-zip-safe
sphinxcontrib_openstreetmap.egg-info/requires.txt
sphinxcontrib_openstreetmap.egg-info/top_level.txt