Metadata-Version: 1.1
Name: sphinxcontrib-openstreetmap
Version: 0.4.0.dev20160401
Summary: Sphinx "OpenStreetMap" extension
Home-page: https://github.com/kenhys/sphinxcontrib-openstreetmap
Author: HAYASHI Kentaro
Author-email: kenhys@gmail.com
License: BSD
Download-URL: http://pypi.python.org/pypi/sphinxcontrib-openstreetmap
Platform: any
Classifier: Development Status :: 4 - Beta
Classifier: Environment :: Console
Classifier: Environment :: Web Environment
Classifier: Intended Audience :: Developers
Classifier: License :: OSI Approved :: BSD License
Classifier: Operating System :: OS Independent
Classifier: Programming Language :: Python
Classifier: Framework :: Sphinx :: Extension
Classifier: Topic :: Documentation
Classifier: Topic :: Utilities
